Workbook

Sheet Pivot table & Charts
A3: Row Labels | B3: Count of gender
A4: Male | B4: 25
A5: Female | B5: 15
A6: Grand Total | B6: 40
A13: Row Labels | B13: Count of Avenue
A14: Mutual Fund | B14: 18
A15: Equity | B15: 10
A16: Fixed Deposits | B16: 9
A17: Public Provident Fund | B17: 3
A18: Grand Total | B18: 40
A26: Row Labels | B26: Count of Mutual_Funds
A27: Better Returns | B27: 24
A28: Fund Diversification | B28: 13
A29: Tax Benefits | B29: 3
A30: Grand Total | B30: 40
A35: Row Labels | B35: Count of Source
A36: Internet | B36: 4
A37: Television | B37: 6
A38: Newspapers and Magazines | B38: 14
A39: Financial Consultants | B39: 16
A40: Grand Total | B40: 40
A47: Row Labels | B47: Count of Duration
A48: 3-5 years | B48: 19
A49: 1-3 years | B49: 18
A50: Less than 1 year | B50: 2
A51: More than 5 years | B51: 1
A52: Grand Total | B52: 40

Sheet Data_set 2 - Copy
A1: gender | B1: age | C1: Investment_Avenues | D1: Mutual_Funds | E1: Equity_Market | F1: Debentures | G1: Government_Bonds | H1: Fixed_Deposits | I1: PPF | J1: Gold | K1: Stock_Marktet | L1: Factor | M1: Objective | N1: Purpose | O1: Duration | P1: Invest_Monitor | Q1: Expect | R1: Avenue | S1: Savings Objective | T1: Reason_Equity | U1: Reason_Mutual | V1: Reason_Bonds | W1: Reason_FD | X1: Source
A2: Female | B2: 34 | C2: Yes | D2: 1 | E2: 2 | F2: 5 | G2: 3 | H2: 7 | I2: 6 | J2: 4 | K2: Yes | L2: Returns | M2: Capital Appreciation | N2: Wealth Creation | O2: 1-3 years | P2: Monthly | Q2: 20%-30% | R2: Mutual Fund | S2: Retirement Plan | T2: Capital Appreciation | U2: Better Returns | V2: Safe Investment | W2: Fixed Returns | X2: Newspapers and Magazines
A3: Female | B3: 23 | C3: Yes | D3: 4 | E3: 3 | F3: 2 | G3: 1 | H3: 5 | I3: 6 | J3: 7 | K3: No | L3: Locking Period | M3: Capital Appreciation | N3: Wealth Creation | O3: More than 5 years | P3: Weekly | Q3: 20%-30% | R3: Mutual Fund | S3: Health Care | T3: Dividend | U3: Better Returns | V3: Safe Investment | W3: High Interest Rates | X3: Financial Consultants
A4: Male | B4: 30 | C4: Yes | D4: 3 | E4: 6 | F4: 4 | G4: 2 | H4: 5 | I4: 1 | J4: 7 | K4: Yes | L4: Returns | M4: Capital Appreciation | N4: Wealth Creation | O4: 3-5 years | P4: Daily | Q4: 20%-30% | R4: Equity | S4: Retirement Plan | T4: Capital Appreciation | U4: Tax Benefits | V4: Assured Returns | W4: Fixed Returns | X4: Television
A5: Male | B5: 22 | C5: Yes | D5: 2 | E5: 1 | F5: 3 | G5: 7 | H5: 6 | I5: 4 | J5: 5 | K5: Yes | L5: Returns | M5: Income | N5: Wealth Creation | O5: Less than 1 year | P5: Daily | Q5: 10%-20% | R5: Equity | S5: Retirement Plan | T5: Dividend | U5: Fund Diversification | V5: Tax Incentives | W5: High Interest Rates | X5: Internet
A6: Female | B6: 24 | C6: No | D6: 2 | E6: 1 | F6: 3 | G6: 6 | H6: 4 | I6: 5 | J6: 7 | K6: No | L6: Returns | M6: Income | N6: Wealth Creation | O6: Less than 1 year | P6: Daily | Q6: 20%-30% | R6: Equity | S6: Retirement Plan | T6: Capital Appreciation | U6: Better Returns | V6: Safe Investment | W6: Risk Free | X6: Internet
A7: Female | B7: 24 | C7: No | D7: 7 | E7: 5 | F7: 4 | G7: 6 | H7: 3 | I7: 1 | J7: 2 | K7: No | L7: Risk | M7: Capital Appreciation | N7: Wealth Creation | O7: 1-3 years | P7: Daily | Q7: 30%-40% | R7: Mutual Fund | S7: Retirement Plan | T7: Liquidity | U7: Fund Diversification | V7: Safe Investment | W7: Risk Free | X7: Internet
A8: Female | B8: 27 | C8: Yes | D8: 3 | E8: 6 | F8: 4 | G8: 2 | H8: 5 | I8: 1 | J8: 7 | K8: Yes | L8: Returns | M8: Capital Appreciation | N8: Wealth Creation | O8: 3-5 years | P8: Monthly | Q8: 20%-30% | R8: Equity | S8: Retirement Plan | T8: Capital Appreciation | U8: Better Returns | V8: Assured Returns | W8: High Interest Rates | X8: Financial Consultants
A9: Male | B9: 21 | C9: Yes | D9: 2 | E9: 3 | F9: 7 | G9: 4 | H9: 6 | I9: 1 | J9: 5 | K9: Yes | L9: Risk | M9: Capital Appreciation | N9: Wealth Creation | O9: 3-5 years | P9: Monthly | Q9: 20%-30% | R9: Mutual Fund | S9: Retirement Plan | T9: Capital Appreciation | U9: Better Returns | V9: Assured Returns | W9: Risk Free | X9: Newspapers and Magazines
A10: Male | B10: 35 | C10: Yes | D10: 2 | E10: 4 | F10: 7 | G10: 5 | H10: 3 | I10: 1 | J10: 6 | K10: Yes | L10: Returns | M10: Growth | N10: Savings for Future | O10: 1-3 years | P10: Weekly | Q10: 20%-30% | R10: Equity | S10: Retirement Plan | T10: Capital Appreciation | U10: Fund Diversification | V10: Safe Investment | W10: Fixed Returns | X10: Television
A11: Male | B11: 31 | C11: Yes | D11: 1 | E11: 3 | F11: 7 | G11: 4 | H11: 5 | I11: 2 | J11: 6 | K11: Yes | L11: Returns | M11: Capital Appreciation | N11: Wealth Creation | O11: 3-5 years | P11: Monthly | Q11: 30%-40% | R11: Fixed Deposits | S11: Retirement Plan | T11: Capital Appreciation | U11: Fund Diversification | V11: Assured Returns | W11: Fixed Returns | X11: Newspapers and Magazines
A12: Female | B12: 35 | C12: Yes | D12: 2 | E12: 4 | F12: 7 | G12: 5 | H12: 3 | I12: 1 | J12: 6 | K12: Yes | L12: Risk | M12: Growth | N12: Savings for Future | O12: 3-5 years | P12: Monthly | Q12: 20%-30% | R12: Mutual Fund | S12: Retirement Plan | T12: Capital Appreciation | U12: Better Returns | V12: Assured Returns | W12: Risk Free | X12: Financial Consultants
A13: Male | B13: 29 | C13: Yes | D13: 2 | E13: 5 | F13: 7 | G13: 6 | H13: 3 | I13: 1 | J13: 4 | K13: Yes | L13: Risk | M13: Capital Appreciation | N13: Wealth Creation | O13: 1-3 years | P13: Monthly | Q13: 20%-30% | R13: Mutual Fund | S13: Retirement Plan | T13: Capital Appreciation | U13: Fund Diversification | V13: Assured Returns | W13: Fixed Returns | X13: Financial Consultants
... A41: Male | B41: 29 | C41: Yes | D41: 4 | E41: 3 | F41: 5 | G41: 7 | H41: 2 | I41: 1 | J41: 6 | K41: Yes | L41: Returns | M41: Capital Appreciation | N41: Wealth Creation | O41: 3-5 years | P41: Monthly | Q41: 20%-30% | R41: Fixed Deposits | S41: Retirement Plan | T41: Dividend | U41: Better Returns | V41: Safe Investment | W41: Fixed Returns | X41: Financial Consultants

Sheet Descriptive Statistics
A1: Column | B1: Mean | C1: Median | D1: Std dev | E1: Min | F1: Max
A2: age | B2: =AVERAGE('Data_set 2 - Copy'!B2:B41) -> 27.8 | C2: =MEDIAN('Data_set 2 - Copy'!B2:B41) -> 27 | D2: =STDEV('Data_set 2 - Copy'!B2:B41) -> 3.5604667 | E2: =MIN('Data_set 2 - Copy'!B2:B41) -> 21 | F2: =MAX('Data_set 2 - Copy'!B2:B41) -> 35
A3: Mutual Funds | B3: =AVERAGE('Data_set 2 - Copy'!D2:D41) -> 2.55 | C3: =MEDIAN('Data_set 2 - Copy'!D2:D41) -> 2 | D3: =STDEV('Data_set 2 - Copy'!D2:D41) -> 1.197219 | E3: =MIN('Data_set 2 - Copy'!D2:D41) -> 1 | F3: =MAX('Data_set 2 - Copy'!D2:D41) -> 7
A4: Equity Market | B4: =AVERAGE('Data_set 2 - Copy'!E2:E41) -> 3.475 | C4: =MEDIAN('Data_set 2 - Copy'!E2:E41) -> 4 | D4: =STDEV('Data_set 2 - Copy'!E2:E41) -> 1.1319939 | E4: =MIN('Data_set 2 - Copy'!E2:E41) -> 1 | F4: =MAX('Data_set 2 - Copy'!E2:E41) -> 6
A5: Debentures | B5: =AVERAGE('Data_set 2 - Copy'!F2:F41) -> 5.75 | C5: =MEDIAN('Data_set 2 - Copy'!F2:F41) -> 6.5 | D5: =STDEV('Data_set 2 - Copy'!F2:F41) -> 1.675617 | E5: =MIN('Data_set 2 - Copy'!F2:F41) -> 1 | F5: =MAX('Data_set 2 - Copy'!F2:F41) -> 7
A6: Government Bonds | B6: =AVERAGE('Data_set 2 - Copy'!G2:G41) -> 4.65 | C6: =MEDIAN('Data_set 2 - Copy'!G2:G41) -> 5 | D6: =STDEV('Data_set 2 - Copy'!G2:G41) -> 1.3690723 | E6: =MIN('Data_set 2 - Copy'!G2:G41) -> 1 | F6: =MAX('Data_set 2 - Copy'!G2:G41) -> 7
A7: Fixed Deposits | B7: =AVERAGE('Data_set 2 - Copy'!H2:H41) -> 3.575 | C7: =MEDIAN('Data_set 2 - Copy'!H2:H41) -> 3.5 | D7: =STDEV('Data_set 2 - Copy'!H2:H41) -> 1.7958285 | E7: =MIN('Data_set 2 - Copy'!H2:H41) -> 1 | F7: =MAX('Data_set 2 - Copy'!H2:H41) -> 7
A8: PPF | B8: =AVERAGE('Data_set 2 - Copy'!I2:I41) -> 2.025 | C8: =MEDIAN('Data_set 2 - Copy'!I2:I41) -> 1 | D8: =STDEV('Data_set 2 - Copy'!I2:I41) -> 1.6090689 | E8: =MIN('Data_set 2 - Copy'!I2:I41) -> 1 | F8: =MAX('Data_set 2 - Copy'!I2:I41) -> 6
A9: Gold | B9: =AVERAGE('Data_set 2 - Copy'!J2:J41) -> 5.975 | C9: =MEDIAN('Data_set 2 - Copy'!J2:J41) -> 6 | D9: =STDEV('Data_set 2 - Copy'!J2:J41) -> 1.1432634 | E9: =MIN('Data_set 2 - Copy'!J2:J41) -> 2 | F9: =MAX('Data_set 2 - Copy'!J2:J41) -> 7
